{
  "ar": {
    "connected": "غير متصل",
    "internet": "من فظلك تحقق من الأنترنيت",
    "address": "عنوان داش",
    "password": "password",
    "language": "اللغة",
    "currency": "العملة المحلية",
    "format": "تنسيق الإفتراضي لداش",
    "save": "حفظ",
    "charge": "شحن",
    "partial": "تم الإستلام",
    "waiting": "إنتظار من اجل الدفع...",
    "cancel": "إلغاء",
    "payment_received": "تم إستلام الدفع",
    "thanks": "شكرا لك!",
    "done": "تم الأمر",
    "pay": "pay",
    "errors": {
      "enter": "Please enter your password",
      "wrong": "Password is incorrect",
      "address": "Please enter a valid Dash address.",
      "warning": "This is a testnet address, please make sure you are using a testnet build!",
      "password": "Please enter a password.\n(must be at least 8 characters)",
      "create": "create a password",
      "reset": "reset your password?",
      "price": "Price cannot be blank. Please enter an amount."
    }
  },

  "de": {
    "connected": "nicht verbunden",
    "internet": "bitte überprüfen Sie Ihr Internet",
    "address": "Dash Adresse",
    "password": "password",
    "language": "Sprache",
    "currency": "Lokale Währung",
    "format": "vorgegebenes Dash Format",
    "save": "speichern",
    "charge": "bezahlen",
    "partial": "erhalten",
    "waiting": "warten auf die Zahlung...",
    "cancel": "abbrechen",
    "payment_received": "Zahlung erhalten!",
    "thanks": "Vielen Dank!",
    "done": "abgeschlossen",
    "pay": "pay",
    "errors": {
      "enter": "Please enter your password",
      "wrong": "Password is incorrect",
      "address": "Please enter a valid Dash address.",
      "warning": "This is a testnet address, please make sure you are using a testnet build!",
      "password": "Please enter a password.\n(must be at least 8 characters)",
      "create": "create a password",
      "reset": "reset your password?",
      "price": "Price cannot be blank. Please enter an amount."
    }
  },

  "en": {
    "connected": "not connected",
    "internet": "please check internet",
    "address": "dash address",
    "password": "password",
    "language": "language",
    "currency": "local currency",
    "format": "default dash format",
    "save": "save",
    "charge": "charge",
    "partial": "received",
    "waiting": "waiting for payment...",
    "cancel": "cancel",
    "payment_received": "Payment Received!",
    "thanks": "Thank you!",
    "done": "done",
    "pay": "pay",
    "errors": {
      "enter": "Please enter your password",
      "wrong": "Password is incorrect",
      "address": "Please enter a valid Dash address.",
      "warning": "This is a testnet address, please make sure you are using a testnet build!",
      "password": "Please enter a password.\n(must be at least 8 characters)",
      "create": "create a password",
      "reset": "reset your password?",
      "price": "Price cannot be blank. Please enter an amount."
    }
  },

  "es": {
    "connected": "no conectado",
    "internet": "por favor revisa tu internet",
    "address": "dirección de dash",
    "password": "clave",
    "language": "idioma",
    "currency": "moneda local",
    "format": "formato predeterminado de dash",
    "save": "guardar",
    "charge": "cobrar",
    "partial": "recibido",
    "waiting": "esperando el pago...",
    "cancel": "cancelar",
    "payment_received": "¡Pago Recibido!",
    "thanks": "¡Gracias!",
    "done": "hecho",
    "pay": "pay",
    "errors": {
      "enter": "Favor ingresar tu clave",
      "wrong": "Clave incorrecta",
      "address": "Favor ingresar una dirección de Dash válida.",
      "warning": "This is a testnet address, please make sure you are using a testnet build!",
      "password": "Favor ingresar una clave.\n(debe ser al menos 8 caracteres)",
      "create": "crear una clave",
      "reset": "restablecer tu clave?",
      "price": "El precio no puede estar en blanco. Favor ingresar una cantidad."
    }
  },

  "fr": {
    "connected": "non connecté",
    "internet": "vérifiez la connexion Internet",
    "address": "adresse Dash",
    "password": "password",
    "language": "langue",
    "currency": "monnaie locale",
    "format": "format Dash par défaut",
    "save": "enregistrer",
    "charge": "à payer",
    "partial": "reçu",
    "waiting": "en attente de paiement...",
    "cancel": "annuler",
    "payment_received": "Paiement reçu !",
    "thanks": "Merci !",
    "done": "terminé",
    "pay": "pay",
    "errors": {
      "enter": "Please enter your password",
      "wrong": "Password is incorrect",
      "address": "Please enter a valid Dash address.",
      "warning": "This is a testnet address, please make sure you are using a testnet build!",
      "password": "Please enter a password.\n(must be at least 8 characters)",
      "create": "create a password",
      "reset": "reset your password?",
      "price": "Price cannot be blank. Please enter an amount."
    }
  },

  "it": {
    "connected": "Non Connesso",
    "internet": "per favore controlla internet",
    "address": "indirizzo dash ",
    "password": "password",
    "language": "lingua",
    "currency": "moneta locale",
    "format": "formato dash predfinito",
    "save": "salva",
    "charge": "addebito",
    "partial": "ricevuto",
    "waiting": "in attesa del pagamento...",
    "cancel": "cancellare",
    "payment_received": "Pagamento Ricevuto!",
    "thanks": "Grazie!",
    "done": "fatto",
    "pay": "pay",
    "errors": {
      "enter": "Please enter your password",
      "wrong": "Password is incorrect",
      "address": "Please enter a valid Dash address.",
      "warning": "This is a testnet address, please make sure you are using a testnet build!",
      "password": "Please enter a password.\n(must be at least 8 characters)",
      "create": "create a password",
      "reset": "reset your password?",
      "price": "Price cannot be blank. Please enter an amount."
    }
  },

  "nl": {
      "connected": "niet verbonden",
      "internet": "controleer de internetverbinding",
      "address": "Dash adres",
      "password": "password",
      "language": "taal",
      "currency": "lokale valuta",
      "format": "standaard Dash eenheid",
      "save": "opslaan",
      "charge": "betalen",
      "partial": "ontvangen",
      "waiting": "wachten op betaling...",
      "cancel": "annuleren",
      "payment_received": "Betaling ontvangen!",
      "thanks": "Bedankt!",
      "done": "voltooid",
      "pay": "pay",
      "errors": {
        "enter": "Please enter your password",
        "wrong": "Password is incorrect",
        "address": "Please enter a valid Dash address.",
        "warning": "This is a testnet address, please make sure you are using a testnet build!",
        "password": "Please enter a password.\n(must be at least 8 characters)",
        "create": "create a password",
        "reset": "reset your password?",
        "price": "Price cannot be blank. Please enter an amount."
      }
    },

  "pl": {
    "connected": "podłączony",
    "internet": "proszę sprawdź połączenie",
    "address": "dash adres",
    "password": "password",
    "language": "język",
    "currency": "lokalna waluta",
    "format": "domyślny format dash",
    "save": "zachowaj",
    "charge": "zapłać",
    "partial": "częściowy",
    "waiting": "czekam na płatność...",
    "cancel": "anuluj",
    "payment_received": "Płatność otrzymana!",
    "thanks": "Dziękuję",
    "done": "zrobione",
    "pay": "pay",
    "errors": {
      "enter": "Please enter your password",
      "wrong": "Password is incorrect",
      "address": "Please enter a valid Dash address.",
      "warning": "This is a testnet address, please make sure you are using a testnet build!",
      "password": "Please enter a password.\n(must be at least 8 characters)",
      "create": "create a password",
      "reset": "reset your password?",
      "price": "Price cannot be blank. Please enter an amount."
    }
  },

  "pt-br": {
      "connected": "desconectado",
      "internet": "por favor verifique internet",
      "address": "endereço dash",
      "password": "password",
      "language": "idioma",
      "currency": "moeda local",
      "format": "formato dash padrão",
      "save": "salvar",
      "charge": "solicitar pagamento",
      "partial": "recebido",
      "waiting": "aguardando pagamento..",
      "cancel": "cancelar",
      "payment_received": "Pagamento recebido!",
      "thanks": "Obrigado!",
      "done": "concluído",
      "pay": "pay",
      "errors": {
        "enter": "Please enter your password",
        "wrong": "Password is incorrect",
        "address": "Please enter a valid Dash address.",
        "warning": "This is a testnet address, please make sure you are using a testnet build!",
        "password": "Please enter a password.\n(must be at least 8 characters)",
        "create": "create a password",
        "reset": "reset your password?",
        "price": "Price cannot be blank. Please enter an amount."
      }
    },

  "sk": {
    "connected": "nepripojené",
    "internet": "prosím skontrolujte pripojenie",
    "address": "dash adresa",
    "password": "password",
    "language": "jazyk",
    "currency": "miestna mena",
    "format": "predvolený formát dash",
    "save": "uložiť",
    "charge": "čiaska",
    "partial": "prijaté",
    "waiting": "čaká sa na platbu...",
    "cancel": "zrušiť",
    "payment_received": "Platba prijatá!",
    "thanks": "Ďakujeme!",
    "done": "hotovo",
    "pay": "pay",
    "errors": {
      "enter": "Please enter your password",
      "wrong": "Password is incorrect",
      "address": "Please enter a valid Dash address.",
      "warning": "This is a testnet address, please make sure you are using a testnet build!",
      "password": "Please enter a password.\n(must be at least 8 characters)",
      "create": "create a password",
      "reset": "reset your password?",
      "price": "Price cannot be blank. Please enter an amount."
    }
  },

  "zh-Hans": {
    "connected": "連接 ",
    "internet": "互連網 ",
    "address": "Dash 地址 ",
    "language": "語言 ",
    "currency": "貨幣 ",
    "format": "格式 ",
    "save": "保存 ",
    "charge": "收費 ",
    "partial": "部分 ",
    "waiting": "等待 ",
    "cancel": "取消 ",
    "payment_received": "付款收到 ",
    "thanks": "謝謝 ",
    "done": "完成 ",
    "pay": "pay",
    "errors": {
      "enter": "Please enter your password",
      "wrong": "Password is incorrect",
      "address": "Please enter a valid Dash address.",
      "warning": "This is a testnet address, please make sure you are using a testnet build!",
      "password": "Please enter a password.\n(must be at least 8 characters)",
      "create": "create a password",
      "reset": "reset your password?",
      "price": "Price cannot be blank. Please enter an amount."
    }
  }
}
